hugegraph_llm/__init__.py
hugegraph_llm/config/__init__.py
hugegraph_llm/config/config.ini
hugegraph_llm/examples/__init__.py
hugegraph_llm/examples/build_kg_test.py
hugegraph_llm/examples/graph_rag_test.py
hugegraph_llm/llms/__init__.py
hugegraph_llm/llms/base.py
hugegraph_llm/llms/ernie_bot.py
hugegraph_llm/llms/init_llm.py
hugegraph_llm/llms/openai.py
hugegraph_llm/operators/__init__.py
hugegraph_llm/operators/graph_rag_task.py
hugegraph_llm/operators/kg_construction_task.py
hugegraph_llm/operators/common_op/__init__.py
hugegraph_llm/operators/common_op/check_schema.py
hugegraph_llm/operators/common_op/nltk_helper.py
hugegraph_llm/operators/common_op/print_result.py
hugegraph_llm/operators/hugegraph_op/__init__.py
hugegraph_llm/operators/hugegraph_op/commit_to_hugegraph.py
hugegraph_llm/operators/hugegraph_op/graph_rag_query.py
hugegraph_llm/operators/hugegraph_op/schema_manager.py
hugegraph_llm/operators/llm_op/__init__.py
hugegraph_llm/operators/llm_op/answer_synthesize.py
hugegraph_llm/operators/llm_op/disambiguate_data.py
hugegraph_llm/operators/llm_op/info_extract.py
hugegraph_llm/operators/llm_op/keyword_extract.py
hugegraph_llm/operators/llm_op/unstructured_data_utils.py
hugegraph_llm/utils/__init__.py
hugegraph_llm/utils/config.py
hugegraph_llm/utils/constants.py
hugegraph_llm/utils/gradio_demo.py
hugegraph_llm-1.3.0.dist-info/METADATA
hugegraph_llm-1.3.0.dist-info/WHEEL
hugegraph_llm-1.3.0.dist-info/top_level.txt
hugegraph_llm-1.3.0.dist-info/RECORD
