Metadata-Version: 2.1
Name: hugegraph-llm
Version: 1.3.0
Summary: Integrating Apache HugeGraph with LLM.
Home-page: https://github.com/apache/incubator-hugegraph-ai
Author: Apache HugeGraph Contributors
Author-email: dev@hugegraph.apache.org
Classifier: Programming Language :: Python :: 3
Classifier: License :: OSI Approved :: Apache Software License
Classifier: Operating System :: OS Independent
Requires-Python: >=3.9
Requires-Dist: openai ==0.28.1
Requires-Dist: retry ==0.9.2
Requires-Dist: tiktoken ==0.5.1
Requires-Dist: nltk ==3.8.1
Requires-Dist: gradio ==4.19.2
